django_esbuild/__init__.py
django_esbuild/admin.py
django_esbuild/apps.py
django_esbuild/conf.py
django_esbuild/management/__init__.py
django_esbuild/management/commands/__init__.py
django_esbuild/management/commands/esbuild.py
django_esbuild/management/commands/esbuild_install.py
django_esbuild/management/commands/esbuilda.py
django_esbuild/migrations/__init__.py
django_esbuild/models.py
django_esbuild/tests.py
django_esbuild/views.py
django_esbuild-0.1.0.dist-info/LICENSE
django_esbuild-0.1.0.dist-info/WHEEL
django_esbuild-0.1.0.dist-info/METADATA
django_esbuild-0.1.0.dist-info/RECORD
